MANIFEST.in
README.txt
setup.cfg
setup.py
XStatic_mobx.egg-info/PKG-INFO
XStatic_mobx.egg-info/SOURCES.txt
XStatic_mobx.egg-info/dependency_links.txt
XStatic_mobx.egg-info/namespace_packages.txt
XStatic_mobx.egg-info/not-zip-safe
XStatic_mobx.egg-info/top_level.txt
xstatic/__init__.py
xstatic/pkg/__init__.py
xstatic/pkg/mobx/__init__.py
xstatic/pkg/mobx/data/mobx.js
xstatic/pkg/mobx/data/mobx.min.js
xstatic/pkg/mobx/data/mobx.umd.js
xstatic/pkg/mobx/data/mobx.umd.min.js