Metadata-Version: 1.0
Name: XStatic-mobx
Version: 5.9.0.1
Summary: mobx 5.9.0 (XStatic packaging standard)
Home-page: https://mobx.js.org/
Author: Thomas Waldmann
Author-email: tw@waldmann-edv.de
License: (same as mobx)
Keywords: mobx xstatic
Platform: any
